{"width":1000,"height":300,"walls":[{"pos":{"x":30,"y":90,"isOuterWall":false}},{"pos":{"x":50,"y":90,"isOuterWall":false}},{"pos":{"x":70,"y":90,"isOuterWall":false}},{"pos":{"x":90,"y":90,"isOuterWall":false}},{"pos":{"x":110,"y":90,"isOuterWall":false}},{"pos":{"x":130,"y":90,"isOuterWall":false}},{"pos":{"x":150,"y":90,"isOuterWall":false}},{"pos":{"x":170,"y":90,"isOuterWall":false}},{"pos":{"x":190,"y":90,"isOuterWall":false}},{"pos":{"x":210,"y":90,"isOuterWall":false}},{"pos":{"x":230,"y":90,"isOuterWall":false}},{"pos":{"x":250,"y":90,"isOuterWall":false}},{"pos":{"x":270,"y":90,"isOuterWall":false}},{"pos":{"x":290,"y":90,"isOuterWall":false}},{"pos":{"x":310,"y":90,"isOuterWall":false}},{"pos":{"x":330,"y":90,"isOuterWall":false}},{"pos":{"x":350,"y":90,"isOuterWall":false}},{"pos":{"x":370,"y":90,"isOuterWall":false}},{"pos":{"x":390,"y":90,"isOuterWall":false}},{"pos":{"x":410,"y":90,"isOuterWall":false}},{"pos":{"x":430,"y":90,"isOuterWall":false}},{"pos":{"x":450,"y":90,"isOuterWall":false}},{"pos":{"x":470,"y":90,"isOuterWall":false}},{"pos":{"x":490,"y":90,"isOuterWall":false}},{"pos":{"x":510,"y":90,"isOuterWall":false}},{"pos":{"x":530,"y":90,"isOuterWall":false}},{"pos":{"x":550,"y":90,"isOuterWall":false}},{"pos":{"x":570,"y":90,"isOuterWall":false}},{"pos":{"x":590,"y":90,"isOuterWall":false}},{"pos":{"x":610,"y":90,"isOuterWall":false}},{"pos":{"x":630,"y":90,"isOuterWall":false}},{"pos":{"x":650,"y":90,"isOuterWall":false}},{"pos":{"x":670,"y":90,"isOuterWall":false}},{"pos":{"x":690,"y":90,"isOuterWall":false}},{"pos":{"x":710,"y":90,"isOuterWall":false}},{"pos":{"x":730,"y":90,"isOuterWall":false}},{"pos":{"x":750,"y":90,"isOuterWall":false}},{"pos":{"x":770,"y":90,"isOuterWall":false}},{"pos":{"x":790,"y":90,"isOuterWall":false}},{"pos":{"x":810,"y":90,"isOuterWall":false}},{"pos":{"x":830,"y":90,"isOuterWall":false}},{"pos":{"x":850,"y":90,"isOuterWall":false}},{"pos":{"x":870,"y":90,"isOuterWall":false}},{"pos":{"x":890,"y":90,"isOuterWall":false}},{"pos":{"x":910,"y":90,"isOuterWall":false}},{"pos":{"x":930,"y":90,"isOuterWall":false}},{"pos":{"x":950,"y":90,"isOuterWall":false}},{"pos":{"x":970,"y":90,"isOuterWall":false}},{"pos":{"x":30,"y":250,"isOuterWall":false}},{"pos":{"x":50,"y":250,"isOuterWall":false}},{"pos":{"x":70,"y":250,"isOuterWall":false}},{"pos":{"x":90,"y":250,"isOuterWall":false}},{"pos":{"x":110,"y":250,"isOuterWall":false}},{"pos":{"x":130,"y":250,"isOuterWall":false}},{"pos":{"x":150,"y":250,"isOuterWall":false}},{"pos":{"x":170,"y":250,"isOuterWall":false}},{"pos":{"x":190,"y":250,"isOuterWall":false}},{"pos":{"x":210,"y":250,"isOuterWall":false}},{"pos":{"x":230,"y":250,"isOuterWall":false}},{"pos":{"x":250,"y":250,"isOuterWall":false}},{"pos":{"x":270,"y":250,"isOuterWall":false}},{"pos":{"x":290,"y":250,"isOuterWall":false}},{"pos":{"x":310,"y":250,"isOuterWall":false}},{"pos":{"x":330,"y":250,"isOuterWall":false}},{"pos":{"x":350,"y":250,"isOuterWall":false}},{"pos":{"x":370,"y":250,"isOuterWall":false}},{"pos":{"x":390,"y":250,"isOuterWall":false}},{"pos":{"x":410,"y":250,"isOuterWall":false}},{"pos":{"x":430,"y":250,"isOuterWall":false}},{"pos":{"x":450,"y":250,"isOuterWall":false}},{"pos":{"x":470,"y":250,"isOuterWall":false}},{"pos":{"x":490,"y":250,"isOuterWall":false}},{"pos":{"x":510,"y":250,"isOuterWall":false}},{"pos":{"x":530,"y":250,"isOuterWall":false}},{"pos":{"x":550,"y":250,"isOuterWall":false}},{"pos":{"x":570,"y":250,"isOuterWall":false}},{"pos":{"x":590,"y":250,"isOuterWall":false}},{"pos":{"x":610,"y":250,"isOuterWall":false}},{"pos":{"x":630,"y":250,"isOuterWall":false}},{"pos":{"x":650,"y":250,"isOuterWall":false}},{"pos":{"x":670,"y":250,"isOuterWall":false}},{"pos":{"x":690,"y":250,"isOuterWall":false}},{"pos":{"x":710,"y":250,"isOuterWall":false}},{"pos":{"x":730,"y":250,"isOuterWall":false}},{"pos":{"x":750,"y":250,"isOuterWall":false}},{"pos":{"x":770,"y":250,"isOuterWall":false}},{"pos":{"x":790,"y":250,"isOuterWall":false}},{"pos":{"x":810,"y":250,"isOuterWall":false}},{"pos":{"x":830,"y":250,"isOuterWall":false}},{"pos":{"x":850,"y":250,"isOuterWall":false}},{"pos":{"x":870,"y":250,"isOuterWall":false}},{"pos":{"x":890,"y":250,"isOuterWall":false}},{"pos":{"x":910,"y":250,"isOuterWall":false}},{"pos":{"x":930,"y":250,"isOuterWall":false}},{"pos":{"x":950,"y":250,"isOuterWall":false}},{"pos":{"x":970,"y":250,"isOuterWall":false}}],"vObjects":[{"pos":{"x":406.85566360291557,"y":198.28192130022458},"color":[255,255,255],"velocity":{"x":-0.5614525654014914,"y":-0.8275089224921288},"velocityMag":1,"isAssailant":false,"goal":{"x":954.5,"y":167.25}},{"pos":{"x":223.6481297576721,"y":147.83878551132352},"color":[255,255,255],"velocity":{"x":0.4448998552621534,"y":0.8955803251454975},"velocityMag":1,"isAssailant":false,"goal":{"x":929.5,"y":177.25}},{"pos":{"x":49.645128897191576,"y":194.23786047828196},"color":[255,255,255],"velocity":{"x":0.9766230739301098,"y":-0.2149589995029359},"velocityMag":1,"isAssailant":false,"goal":{"x":946.5,"y":186.25}},{"pos":{"x":120.59786676544782,"y":168.2480725417542},"color":[255,255,255],"velocity":{"x":0.6523809446635748,"y":0.757891221112807},"velocityMag":1,"isAssailant":false,"goal":{"x":938.5,"y":180.25}},{"pos":{"x":873.0052574609281,"y":188.9103370410298},"color":[255,255,255],"velocity":{"x":0.4460535819489071,"y":0.8950062580957463},"velocityMag":1,"isAssailant":false,"goal":{"x":944.5,"y":178.25}},{"pos":{"x":201.82502611823557,"y":130.87525642340418},"color":[255,255,255],"velocity":{"x":-0.939911006730896,"y":-0.34141953580033124},"velocityMag":1,"isAssailant":false,"goal":{"x":46.5,"y":159.25}},{"pos":{"x":870.1160059199367,"y":222.44942137621354},"color":[255,255,255],"velocity":{"x":0.9198398306706078,"y":0.3922941318855886},"velocityMag":1,"isAssailant":false,"goal":{"x":73.5,"y":166.25}},{"pos":{"x":303.2052295408843,"y":163.9132219883507},"color":[255,255,255],"velocity":{"x":0.538000716755678,"y":0.8429443805912563},"velocityMag":1,"isAssailant":false,"goal":{"x":60.5,"y":169.25}},{"pos":{"x":143.88751757235124,"y":173.1086006786775},"color":[255,255,255],"velocity":{"x":0.7380022538660316,"y":0.6747982463586116},"velocityMag":1,"isAssailant":false,"goal":{"x":85.5,"y":167.25}},{"pos":{"x":316.40937681504977,"y":177.47327686754318},"color":[255,255,255],"velocity":{"x":-0.9479317580179536,"y":-0.31847351874369706},"velocityMag":1,"isAssailant":false,"goal":{"x":76.5,"y":165.25}},{"pos":{"x":358.8502578640012,"y":165.8326209531535},"color":[255,255,255],"velocity":{"x":0.9499049434988434,"y":-0.3125389548783626},"velocityMag":1,"isAssailant":false,"goal":{"x":58.5,"y":163.25}},{"pos":{"x":351.7371013585311,"y":183.2041281450033},"color":[255,255,255],"velocity":{"x":0.08355286344685166,"y":-0.996503346211056},"velocityMag":1,"isAssailant":false,"goal":{"x":73.5,"y":166.25}},{"pos":{"x":237.4252692408063,"y":164.67886625442844},"color":[255,255,255],"velocity":{"x":-0.3168047540889353,"y":-0.948490773696112},"velocityMag":1,"isAssailant":false,"goal":{"x":112.5,"y":153.25}},{"pos":{"x":444.9013481248548,"y":126.05457580222793},"color":[255,255,255],"velocity":{"x":0.7319482049065665,"y":0.6813602757235373},"velocityMag":1,"isAssailant":false,"goal":{"x":920.5,"y":163.25}},{"pos":{"x":438.6194323193605,"y":230.55517184810984},"color":[255,255,255],"velocity":{"x":-0.18905024387881825,"y":0.9819674155945091},"velocityMag":1,"isAssailant":false,"goal":{"x":897.5,"y":183.25}},{"pos":{"x":654.9244115759102,"y":160.0018796540981},"color":[255,255,255],"velocity":{"x":0.4228845353373968,"y":0.906183573991757},"velocityMag":1,"isAssailant":false,"goal":{"x":64.5,"y":149.25}},{"pos":{"x":777.9180287678242,"y":189.59319582486066},"color":[255,255,255],"velocity":{"x":-0.548513552764959,"y":0.8361416640935689},"velocityMag":1,"isAssailant":false,"goal":{"x":68.5,"y":164.25}},{"pos":{"x":833.8019740531512,"y":223.35242930717217},"color":[255,255,255],"velocity":{"x":-0.8002544510392515,"y":0.5996605819894002},"velocityMag":1,"isAssailant":false,"goal":{"x":55.5,"y":193.25}},{"pos":{"x":894.1905414688099,"y":199.8403964330142},"color":[255,255,255],"velocity":{"x":0.6188864755149822,"y":-0.7854804456029719},"velocityMag":1,"isAssailant":false,"goal":{"x":78.5,"y":195.25}},{"pos":{"x":260.52346639255995,"y":156.57365848656625},"color":[255,255,255],"velocity":{"x":-0.6350533087625695,"y":-0.7724683132852198},"velocityMag":1,"isAssailant":false,"goal":{"x":52.5,"y":189.25}},{"pos":{"x":135.61364440089798,"y":197.31658836104262},"color":[255,255,255],"velocity":{"x":-0.63536132270735,"y":0.7722149892404101},"velocityMag":1,"isAssailant":false,"goal":{"x":908.5,"y":171.25}},{"pos":{"x":865.0084273487078,"y":168.68949219083555},"color":[255,255,255],"velocity":{"x":-0.18308810770734,"y":0.9830965083938329},"velocityMag":1,"isAssailant":false,"goal":{"x":919.5,"y":179.25}},{"pos":{"x":269.40073706803344,"y":147.24025958601885},"color":[255,255,255],"velocity":{"x":0.7324842095281586,"y":-0.680784020664343},"velocityMag":1,"isAssailant":false,"goal":{"x":75.5,"y":157.25}},{"pos":{"x":284.8203341720905,"y":192.9724285736517},"color":[255,255,255],"velocity":{"x":-0.0982148529505873,"y":-0.9951652338480753},"velocityMag":1,"isAssailant":false,"goal":{"x":81.5,"y":195.25}},{"pos":{"x":639.7168822142376,"y":205.27624111833865},"color":[255,255,255],"velocity":{"x":-0.9381188956213458,"y":-0.34631335186242324},"velocityMag":1,"isAssailant":false,"goal":{"x":915.5,"y":160.25}},{"pos":{"x":389.64588786443136,"y":178.51018959880494},"color":[255,255,255],"velocity":{"x":-0.9741241217098937,"y":0.2260137064492511},"velocityMag":1,"isAssailant":false,"goal":{"x":90.5,"y":172.25}},{"pos":{"x":525.0180391506977,"y":135.8260500676327},"color":[255,255,255],"velocity":{"x":0.6296356867034779,"y":0.7768905341355626},"velocityMag":1,"isAssailant":false,"goal":{"x":916.5,"y":180.25}},{"pos":{"x":475.4623708513685,"y":157.26266040110656},"color":[255,255,255],"velocity":{"x":0.19292953155754328,"y":0.9812126150090952},"velocityMag":1,"isAssailant":false,"goal":{"x":917.5,"y":173.25}},{"pos":{"x":413.52059506880437,"y":202.15636823219728},"color":[255,255,255],"velocity":{"x":0.8823015880469641,"y":0.47068450976190535},"velocityMag":1,"isAssailant":false,"goal":{"x":934.5,"y":184.25}},{"pos":{"x":173.24171448021232,"y":161.92729505970917},"color":[255,255,255],"velocity":{"x":-0.49310887546487303,"y":0.8699676068324431},"velocityMag":1,"isAssailant":false,"goal":{"x":931.5,"y":172.25}},{"pos":{"x":557.6632375031986,"y":187.634647216086},"color":[255,255,255],"velocity":{"x":0.3245602239470791,"y":-0.9458650332005205},"velocityMag":1,"isAssailant":false,"goal":{"x":108.5,"y":159.25}},{"pos":{"x":767.5854113165898,"y":189.10937663473624},"color":[255,255,255],"velocity":{"x":0.9594385840858969,"y":-0.2819177244645136},"velocityMag":1,"isAssailant":false,"goal":{"x":86.5,"y":142.25}},{"pos":{"x":909.7000027162297,"y":192.2622891193133},"color":[255,255,255],"velocity":{"x":-0.8562309209582327,"y":0.5165932732769725},"velocityMag":1,"isAssailant":false,"goal":{"x":69.5,"y":163.25}},{"pos":{"x":317.8093865903274,"y":149.911890504507},"color":[255,255,255],"velocity":{"x":-0.9927528779898424,"y":0.12017372109943653},"velocityMag":1,"isAssailant":false,"goal":{"x":79.5,"y":145.25}},{"pos":{"x":878.9404961082591,"y":148.15402022770624},"color":[255,255,255],"velocity":{"x":0.4048960759973328,"y":-0.9143627112048928},"velocityMag":1,"isAssailant":false,"goal":{"x":901.5,"y":157.25}},{"pos":{"x":248.13454748676935,"y":194.6563576899559},"color":[255,255,255],"velocity":{"x":0.6440262223669222,"y":-0.7650034149621764},"velocityMag":1,"isAssailant":false,"goal":{"x":78.5,"y":165.25}},{"pos":{"x":584.940496101202,"y":173.91724718491935},"color":[255,255,255],"velocity":{"x":0.8540379371883368,"y":0.5202107283044926},"velocityMag":1,"isAssailant":false,"goal":{"x":928.5,"y":143.25}},{"pos":{"x":482.6653267772769,"y":123.55939549490473},"color":[255,255,255],"velocity":{"x":0.6468375820950454,"y":0.7626277875801769},"velocityMag":1,"isAssailant":false,"goal":{"x":934.5,"y":170.25}},{"pos":{"x":500.25917966665105,"y":209.41176892182565},"color":[255,255,255],"velocity":{"x":-0.8585133326657813,"y":-0.512791241769098},"velocityMag":1,"isAssailant":false,"goal":{"x":913.5,"y":160.25}},{"pos":{"x":314.01373103925835,"y":133.70037971200267},"color":[255,255,255],"velocity":{"x":0.7036670030046335,"y":0.7105299070992559},"velocityMag":1,"isAssailant":false,"goal":{"x":938.5,"y":160.25}},{"pos":{"x":826.3606357344577,"y":156.43480127914208},"color":[255,255,255],"velocity":{"x":0.7680511892459617,"y":-0.6403884529704326},"velocityMag":1,"isAssailant":false,"goal":{"x":87.5,"y":189.25}},{"pos":{"x":911.6868254327393,"y":160.72167775440775},"color":[255,255,255],"velocity":{"x":0.6868662614854387,"y":0.7267838322589577},"velocityMag":1,"isAssailant":false,"goal":{"x":81.5,"y":195.25}},{"pos":{"x":214.04576460076365,"y":210.83214530433813},"color":[255,255,255],"velocity":{"x":0.9932430525588891,"y":0.11605274035325455},"velocityMag":1,"isAssailant":false,"goal":{"x":81.5,"y":194.25}},{"pos":{"x":700.5253777085557,"y":222.21468198801023},"color":[255,255,255],"velocity":{"x":0.4604606410114837,"y":-0.8876801214848137},"velocityMag":1,"isAssailant":false,"goal":{"x":916.5,"y":166.25}},{"pos":{"x":615.2928321509444,"y":113.4141686402694},"color":[255,255,255],"velocity":{"x":-0.5512727103564877,"y":0.8343251157769446},"velocityMag":1,"isAssailant":false,"goal":{"x":926.5,"y":169.25}},{"pos":{"x":647.8073006074188,"y":136.1645438890765},"color":[255,255,255],"velocity":{"x":0.9906751829869328,"y":-0.13624493316746578},"velocityMag":1,"isAssailant":false,"goal":{"x":909.5,"y":150.25}},{"pos":{"x":571.1064917263266,"y":165.14210786283752},"color":[255,255,255],"velocity":{"x":0.20911235816615156,"y":0.9778916206115027},"velocityMag":1,"isAssailant":false,"goal":{"x":931.5,"y":180.25}},{"pos":{"x":529.1955806742887,"y":228.02809240586564},"color":[255,255,255],"velocity":{"x":-0.7617804786715258,"y":0.6478352431868624},"velocityMag":1,"isAssailant":false,"goal":{"x":910.5,"y":196.25}},{"pos":{"x":492.1055232959775,"y":195.97811159910532},"color":[255,255,255],"velocity":{"x":0.9761181171111527,"y":-0.21724046917500903},"velocityMag":1,"isAssailant":false,"goal":{"x":80.5,"y":160.25}},{"pos":{"x":728.1973057255215,"y":196.5592484023244},"color":[255,255,255],"velocity":{"x":-0.5902868440041031,"y":-0.8071935590647856},"velocityMag":1,"isAssailant":false,"goal":{"x":71.5,"y":163.25}},{"pos":{"x":538.7050847800523,"y":158.4766597487179},"color":[255,255,255],"velocity":{"x":-0.7189678275593057,"y":0.6950433532770833},"velocityMag":1,"isAssailant":false,"goal":{"x":99.5,"y":174.25}},{"pos":{"x":278.4888413830611,"y":179.93851838393476},"color":[255,255,255],"velocity":{"x":0.004374873259493196,"y":0.9999904301961912},"velocityMag":1,"isAssailant":false,"goal":{"x":930.5,"y":142.25}},{"pos":{"x":196.1891640794,"y":225.1735580026653},"color":[255,255,255],"velocity":{"x":-0.8059442451126814,"y":0.5919914473788875},"velocityMag":1,"isAssailant":false,"goal":{"x":930.5,"y":154.25}},{"pos":{"x":838.2348608340832,"y":131.461984538166},"color":[255,255,255],"velocity":{"x":0.7544893775585639,"y":0.6563122573526193},"velocityMag":1,"isAssailant":false,"goal":{"x":73.5,"y":151.25}},{"pos":{"x":244.062830393244,"y":231.23345177977006},"color":[255,255,255],"velocity":{"x":-0.3519808478463693,"y":0.9360072022956613},"velocityMag":1,"isAssailant":false,"goal":{"x":910.5,"y":179.25}},{"pos":{"x":166.90975172358023,"y":185.32757014545723},"color":[255,255,255],"velocity":{"x":-0.5910353288863355,"y":-0.8066456719081937},"velocityMag":1,"isAssailant":false,"goal":{"x":917.5,"y":151.25}},{"pos":{"x":916.6037472201805,"y":143.24374821021192},"color":[255,255,255],"velocity":{"x":-0.5733340605273666,"y":-0.819321704240283},"velocityMag":1,"isAssailant":false,"goal":{"x":924.5,"y":150.25}},{"pos":{"x":132.12421971181877,"y":191.50903845274198},"color":[255,255,255],"velocity":{"x":0.626658659030504,"y":-0.779293863097927},"velocityMag":1,"isAssailant":false,"goal":{"x":921.5,"y":151.25}},{"pos":{"x":112.45566727667126,"y":149.91943506602726},"color":[255,255,255],"velocity":{"x":0.9859107144598064,"y":0.16727242185534982},"velocityMag":1,"isAssailant":false,"goal":{"x":67.5,"y":146.25}},{"pos":{"x":166.1007857973687,"y":131.28262782569175},"color":[255,255,255],"velocity":{"x":-0.7531686250720222,"y":-0.6578275018628512},"velocityMag":1,"isAssailant":false,"goal":{"x":85.5,"y":151.25}},{"pos":{"x":188.9273305485393,"y":168.35679510445277},"color":[255,255,255],"velocity":{"x":-0.8103044630832871,"y":-0.5860091100890035},"velocityMag":1,"isAssailant":false,"goal":{"x":93.5,"y":154.25}},{"pos":{"x":756.1079514117737,"y":112.08112111784169},"color":[255,255,255],"velocity":{"x":-0.7101482183226262,"y":-0.7040522054600777},"velocityMag":1,"isAssailant":false,"goal":{"x":936.5,"y":161.25}},{"pos":{"x":711.9202850606026,"y":116.9301629897584},"color":[255,255,255],"velocity":{"x":-0.9490535166130192,"y":0.3151149355464792},"velocityMag":1,"isAssailant":false,"goal":{"x":919.5,"y":165.25}},{"pos":{"x":668.3663059495321,"y":170.3937108706584},"color":[255,255,255],"velocity":{"x":0.9999713735107724,"y":-0.007566515643244615},"velocityMag":1,"isAssailant":false,"goal":{"x":948.5,"y":166.25}},{"pos":{"x":397.27510469105073,"y":151.55449943717417},"color":[255,255,255],"velocity":{"x":-0.9848523248116127,"y":0.17339520844925843},"velocityMag":1,"isAssailant":false,"goal":{"x":65.5,"y":153.25}},{"pos":{"x":416.53171709139895,"y":190.32093575706378},"color":[255,255,255],"velocity":{"x":-0.23895993009080896,"y":0.9710294289108831},"velocityMag":1,"isAssailant":false,"goal":{"x":79.5,"y":167.25}},{"pos":{"x":536.6089452717661,"y":131.19986522871028},"color":[255,255,255],"velocity":{"x":0.8136178523751308,"y":0.5814000260547636},"velocityMag":1,"isAssailant":false,"goal":{"x":899.5,"y":137.25}},{"pos":{"x":513.5,"y":168.25},"color":"#008000","velocity":{"x":0.0008386550029817819,"y":0.9999996483288311},"velocityMag":1,"isAssailant":true},{"pos":{"x":944,"y":162.25},"color":[255,255,255],"velocity":{"x":-0.5037725508528319,"y":0.8638363369338146},"velocityMag":1,"isAssailant":false,"goal":{"x":62,"y":135.25}},{"pos":{"x":65,"y":208.25},"color":[255,255,255],"velocity":{"x":-0.9965065191325014,"y":-0.08351501258112537},"velocityMag":1,"isAssailant":false,"goal":{"x":945,"y":126.25}},{"pos":{"x":67,"y":133.25},"color":[255,255,255],"velocity":{"x":-0.26300124776121825,"y":0.9647954931880861},"velocityMag":1,"isAssailant":false,"goal":{"x":948,"y":211.25}},{"pos":{"x":942,"y":129.25},"color":[255,255,255],"velocity":{"x":-0.1933647975264066,"y":0.981126931175356},"velocityMag":1,"isAssailant":false,"goal":{"x":43,"y":172.25}},{"pos":{"x":944,"y":216.25},"color":[255,255,255],"velocity":{"x":0.5304371258204593,"y":-0.8477242803832684},"velocityMag":1,"isAssailant":false,"goal":{"x":48,"y":157.25}},{"pos":{"x":896,"y":117.25},"color":[255,255,255],"velocity":{"x":0.7973550442271866,"y":0.6035105081483348},"velocityMag":1,"isAssailant":false,"goal":{"x":48,"y":166.25}},{"pos":{"x":388,"y":123.25},"color":[255,255,255],"velocity":{"x":-0.5129133989254941,"y":0.8584403562290726},"velocityMag":1,"isAssailant":false,"goal":{"x":58,"y":156.25}},{"pos":{"x":731,"y":149.25},"color":[255,255,255],"velocity":{"x":0.7760875060582169,"y":0.6306252317663298},"velocityMag":1,"isAssailant":false,"goal":{"x":69,"y":163.25}},{"pos":{"x":767,"y":217.25},"color":[255,255,255],"velocity":{"x":-0.8515254671603113,"y":-0.5243132448998534},"velocityMag":1,"isAssailant":false,"goal":{"x":65,"y":164.25}},{"pos":{"x":292,"y":213.25},"color":[255,255,255],"velocity":{"x":-0.8700314395643083,"y":-0.4929962415370501},"velocityMag":1,"isAssailant":false,"goal":{"x":62,"y":170.25}},{"pos":{"x":353,"y":219.25},"color":[255,255,255],"velocity":{"x":0.8194372331699923,"y":-0.5731689287589722},"velocityMag":1,"isAssailant":false,"goal":{"x":68,"y":156.25}},{"pos":{"x":348,"y":124.25},"color":[255,255,255],"velocity":{"x":0.451321925518234,"y":0.8923612046399785},"velocityMag":1,"isAssailant":false,"goal":{"x":61,"y":149.25}},{"pos":{"x":619,"y":146.25},"color":[255,255,255],"velocity":{"x":-0.9276213878863054,"y":0.37352183434959263},"velocityMag":1,"isAssailant":false,"goal":{"x":59,"y":161.25}},{"pos":{"x":64,"y":121.25},"color":[255,255,255],"velocity":{"x":-0.996391338421642,"y":0.0848781521849343},"velocityMag":1,"isAssailant":false,"goal":{"x":927,"y":176.25}},{"pos":{"x":272,"y":125.25},"color":[255,255,255],"velocity":{"x":0.6134579550170831,"y":-0.7897273817123593},"velocityMag":1,"isAssailant":false,"goal":{"x":913,"y":177.25}},{"pos":{"x":622,"y":221.25},"color":[255,255,255],"velocity":{"x":-0.3156178107555972,"y":0.948886398645193},"velocityMag":1,"isAssailant":false,"goal":{"x":930,"y":186.25}},{"pos":{"x":618,"y":171.25},"color":[255,255,255],"velocity":{"x":-0.31081714333169597,"y":-0.9504697277720758},"velocityMag":1,"isAssailant":false,"goal":{"x":933,"y":180.25}},{"pos":{"x":570,"y":127.25},"color":[255,255,255],"velocity":{"x":0.9906693429261599,"y":0.13628739114918362},"velocityMag":1,"isAssailant":false,"goal":{"x":956,"y":189.25}},{"pos":{"x":450,"y":184.25},"color":[255,255,255],"velocity":{"x":0.11175623222723359,"y":-0.9937356512465338},"velocityMag":1,"isAssailant":false,"goal":{"x":946,"y":182.25}},{"pos":{"x":360,"y":140.25},"color":[255,255,255],"velocity":{"x":-0.9952612412355369,"y":-0.09723714153706015},"velocityMag":1,"isAssailant":false,"goal":{"x":948,"y":191.25}},{"pos":{"x":132,"y":223.25},"color":[255,255,255],"velocity":{"x":0.7076975872292675,"y":-0.7065154810971048},"velocityMag":1,"isAssailant":false,"goal":{"x":936,"y":199.25}},{"pos":{"x":83,"y":163.25},"color":[255,255,255],"velocity":{"x":0.944627780490704,"y":0.3281438043376812},"velocityMag":1,"isAssailant":false,"goal":{"x":948,"y":149.25}},{"pos":{"x":95,"y":200.25},"color":[255,255,255],"velocity":{"x":-0.9717625928179286,"y":0.2359607238499165},"velocityMag":1,"isAssailant":false,"goal":{"x":953,"y":199.25}}],"globalGoalX":513.5,"globalGoalY":46.25,"useGlobalAndLocalGoals":true,"showAssailantArcs":true,"showPedestrianArcs":false}